MANIFEST.in
setup.cfg
setup.py
versioneer.py
chalmers/__init__.py
chalmers/_version.py
chalmers/config.py
chalmers/errors.py
chalmers/event_dispatcher.py
chalmers/program_manager.py
chalmers.egg-info/PKG-INFO
chalmers.egg-info/SOURCES.txt
chalmers.egg-info/dependency_links.txt
chalmers.egg-info/entry_points.txt
chalmers.egg-info/requires.txt
chalmers.egg-info/top_level.txt
chalmers/commands/__init__.py
chalmers/commands/add.py
chalmers/commands/at_login.py
chalmers/commands/at_startup.py
chalmers/commands/bg.py
chalmers/commands/edit.py
chalmers/commands/export.py
chalmers/commands/import.py
chalmers/commands/list.py
chalmers/commands/log.py
chalmers/commands/procfile.py
chalmers/commands/remove.py
chalmers/commands/set.py
chalmers/commands/show.py
chalmers/commands/start.py
chalmers/commands/stop.py
chalmers/program/__init__.py
chalmers/program/base.py
chalmers/program/nt.py
chalmers/program/posix.py
chalmers/program/utils.py
chalmers/program/tests/__init__.py
chalmers/program/tests/test_nt_program.py
chalmers/program/tests/test_posix_program.py
chalmers/program/tests/test_program.py
chalmers/scripts/__init__.py
chalmers/scripts/chalmers_main.py
chalmers/scripts/runner.py
chalmers/scripts/service.py
chalmers/service/__init__.py
chalmers/service/cron_service.py
chalmers/service/darwin_service.py
chalmers/service/posix_service.py
chalmers/service/systemd_service.py
chalmers/service/sysv_service.py
chalmers/service/upstart_service.py
chalmers/service/win32_local_service.py
chalmers/service/win32_system_service.py
chalmers/service/data/launchd.plist
chalmers/service/data/systemd.service
chalmers/service/data/sysv-init.sh
chalmers/service/data/upstart.conf
chalmers/service/tests/__init__.py
chalmers/service/tests/test_cron_service.py
chalmers/service/tests/test_darwin_service.py
chalmers/service/tests/test_systemd_service.py
chalmers/tests/__init__.py
chalmers/tests/test_commands.py
chalmers/tests/test_event_dispatcher.py
chalmers/tests/test_program_manager.py
chalmers/utils/__init__.py
chalmers/utils/appdirs.py
chalmers/utils/cli.py
chalmers/utils/color_picker.py
chalmers/utils/daemonize.py
chalmers/utils/file_echo.py
chalmers/utils/kill_tree.py
