Metadata-Version: 1.0
Name: chalmers
Version: 0.7.9
Summary: Process Control System
Home-page: http://github.com/binstar/chalmers
Author: Continuum Analytics
Author-email: srossross@gmail.com
License: UNKNOWN
Platform: UNKNOWN
